setup.cfg
setup.py
hamms/__init__.py
hamms/__main__.py
hamms/morse.py
hamms.egg-info/PKG-INFO
hamms.egg-info/SOURCES.txt
hamms.egg-info/dependency_links.txt
hamms.egg-info/requires.txt
hamms.egg-info/top_level.txt