Metadata-Version: 1.0
Name: hamms
Version: 1.3
Summary: Malformed servers to test your HTTP client
Home-page: https://github.com/kevinburke/hamms
Author: Kevin Burke
Author-email: kev@inburke.com
License: UNKNOWN
Keywords: testing,server,http
Platform: UNKNOWN
